ipmus_data_convertor_cli/__init__.py
ipmus_data_convertor_cli/__main__.py
ipmus_data_convertor_cli/convertor.py
ipmusconvertor-1.0.3.dist-info/METADATA
ipmusconvertor-1.0.3.dist-info/WHEEL
ipmusconvertor-1.0.3.dist-info/dependency_links.txt
ipmusconvertor-1.0.3.dist-info/entry_points.txt
ipmusconvertor-1.0.3.dist-info/top_level.txt
ipmusconvertor-1.0.3.dist-info/RECORD
